bidsphysio.pmu2bids-21.6.24-py3.8-nspkg.pth
bidsphysio/pmu2bids/__init__.py
bidsphysio/pmu2bids/info.py
bidsphysio/pmu2bids/pmu2bidsphysio.py
tests/__init__.py
tests/test_pmu2bidsphysio.py
tests/utils.py
bidsphysio.pmu2bids-21.6.24.dist-info/METADATA
bidsphysio.pmu2bids-21.6.24.dist-info/WHEEL
bidsphysio.pmu2bids-21.6.24.dist-info/entry_points.txt
bidsphysio.pmu2bids-21.6.24.dist-info/namespace_packages.txt
bidsphysio.pmu2bids-21.6.24.dist-info/top_level.txt
bidsphysio.pmu2bids-21.6.24.dist-info/RECORD
